newspaperV3/__init__.py
newspaperV3/api.py
newspaperV3/article.py
newspaperV3/cleaners.py
newspaperV3/configuration.py
newspaperV3/extractors.py
newspaperV3/images.py
newspaperV3/mthreading.py
newspaperV3/network.py
newspaperV3/nlp.py
newspaperV3/outputformatters.py
newspaperV3/parsers.py
newspaperV3/resources/misc/google_sources.txt
newspaperV3/resources/misc/popular_sources.txt
newspaperV3/resources/misc/stopwords-nlp-en.txt
newspaperV3/resources/misc/useragents.txt
newspaperV3/resources/text/stopwords-ar.txt
newspaperV3/resources/text/stopwords-be.txt
newspaperV3/resources/text/stopwords-bg.txt
newspaperV3/resources/text/stopwords-da.txt
newspaperV3/resources/text/stopwords-de.txt
newspaperV3/resources/text/stopwords-el.txt
newspaperV3/resources/text/stopwords-en.txt
newspaperV3/resources/text/stopwords-es.txt
newspaperV3/resources/text/stopwords-et.txt
newspaperV3/resources/text/stopwords-fa.txt
newspaperV3/resources/text/stopwords-fi.txt
newspaperV3/resources/text/stopwords-fr.txt
newspaperV3/resources/text/stopwords-he.txt
newspaperV3/resources/text/stopwords-hi.txt
newspaperV3/resources/text/stopwords-hr.txt
newspaperV3/resources/text/stopwords-hu.txt
newspaperV3/resources/text/stopwords-id.txt
newspaperV3/resources/text/stopwords-it.txt
newspaperV3/resources/text/stopwords-ja.txt
newspaperV3/resources/text/stopwords-ko.txt
newspaperV3/resources/text/stopwords-lt.txt
newspaperV3/resources/text/stopwords-mk.txt
newspaperV3/resources/text/stopwords-nb.txt
newspaperV3/resources/text/stopwords-nl.txt
newspaperV3/resources/text/stopwords-no.txt
newspaperV3/resources/text/stopwords-pl.txt
newspaperV3/resources/text/stopwords-pt.txt
newspaperV3/resources/text/stopwords-ro.txt
newspaperV3/resources/text/stopwords-ru.txt
newspaperV3/resources/text/stopwords-sl.txt
newspaperV3/resources/text/stopwords-sr.txt
newspaperV3/resources/text/stopwords-sv.txt
newspaperV3/resources/text/stopwords-sw.txt
newspaperV3/resources/text/stopwords-th.txt
newspaperv3-0.3.2.dist-info/LICENSE
newspaperv3-0.3.2.dist-info/METADATA
newspaperv3-0.3.2.dist-info/WHEEL
newspaperv3-0.3.2.dist-info/RECORD
