Metadata-Version: 2.3
Name: newspaperV3
Version: 0.3.2
Summary: Advanced news extraction, article parsing, and content analysis.
License: MIT
Keywords: newspaper,news,article,extraction,scraping,nlp,content,parsing
Author: Lucas Ou-Yang
Requires-Python: >=3.8,<4.0
Classifier: Development Status :: 4 - Beta
Classifier: Intended Audience :: Developers
Classifier: License :: OSI Approved :: MIT License
Classifier: Operating System :: OS Independent
Classifier: Programming Language :: Python :: 3
Classifier: Programming Language :: Python :: 3.8
Classifier: Programming Language :: Python :: 3.9
Classifier: Programming Language :: Python :: 3.10
Classifier: Programming Language :: Python :: 3.11
Classifier: Programming Language :: Python :: 3.12
Classifier: Programming Language :: Python :: 3.13
Classifier: Topic :: Software Development :: Libraries :: Python Modules
Classifier: Topic :: Text Processing
Requires-Dist: Pillow (>=8.1.2)
Requires-Dist: beautifulsoup4 (>=4.9.3)
Requires-Dist: cssselect (>=1.1.0)
Requires-Dist: dateparser (>=1.1.0)
Requires-Dist: feedfinder2 (>=0.0.4)
Requires-Dist: feedparser (>=6.0.2)
Requires-Dist: jieba3k (>=0.35.1)
Requires-Dist: lxml (>=4.6.2)
Requires-Dist: nltk (>=3.6.2)
Requires-Dist: python-dateutil (>=2.8.1)
Requires-Dist: requests (>=2.25.1)
Requires-Dist: tinysegmenter (>=0.3)
Requires-Dist: tldextract (>=3.1.0)
Project-URL: Homepage, https://github.com/salah55s/newspaperV3
Project-URL: Repository, https://github.com/salah55s/newspaperV3
